<?xml version="1.0" encoding="UTF-8" standalone="yes"?>

<product>
  <id>13-02-keukenkast</id>  
  <name>.13-02 Keukenkast</name>
  <htmlTitle>keukenkast .13-02 | Meubelmakerij Tommiek</htmlTitle>
  <metaDescription>grote eiken keukenkast op maat</metaDescription>
  <metaKeywords>keuken, keukenkast, greeploos, eiken kast</metaKeywords>


  <leadText><![CDATA[
  greeploos voor in de keuken...
  ]]></leadText>
  <leadImage>    
	<src>tommiek-13-02-keukenkast-lead.jpg</src>
    <alt>.13-02 Keukenkast</alt>
  </leadImage>
  
  <description><![CDATA[
  <p>In de keuken van dit huis was dringend behoefte aan extra kastruimte. In de hal was ook opbergruimte nodig. De oplossing was bedacht: een kast voor extra keukenspullen &eactue;n om spullen voor naar buiten (schoenen, tassen e.d.) te kunnen opbergen.</p>
  <p>Deze kast is het resultaat. In gemakkelijk te openen lades kunnen schoenen worden opgeborgen, in het open vak tassen en dergelijke en de kastruimte erboven wordt gebruikt voor de keukenspullen.</p>
    ]]></description>

  <details><![CDATA[
	   <h2>.13-02 Keukenkast</h2>
	   Ontwerp: Tommiek<br/>
	   Serie: Greeploze kasten
	   <h2>Details</h2>
	   massief eikenhouten fronts, kast van MDF met eiken fineer, <br/>
	   afwerking: hoogwaardige meubelolie met wit pigment.

  ]]></details>


  <images>
    <image>
      <thumb>tommiek-13-02-keukenkast-01.jpg</thumb>
      <src>tommiek-13-02-keukenkast-01.jpg</src>
      <alt>.13-02 Keukenkast</alt>
    </image>
    <image>
      <thumb>tommiek-13-02-keukenkast-03.jpg</thumb>
      <src>tommiek-13-02-keukenkast-03.jpg</src>
      <alt>.13-02 Keukenkast</alt>
    </image>
    <image>
      <thumb>tommiek-13-02-keukenkast-02.jpg</thumb>
      <src>tommiek-13-02-keukenkast-02.jpg</src>
      <alt>.13-02 Keukenkast</alt>
    </image>
    </images>

</product>